pyqpanda_alg/__init__.py
pyqpanda_alg/libcurl.dll
pyqpanda_alg/msvcr120.dll
pyqpanda_alg/plugin.cp311-win_amd64.pyd
pyqpanda_alg/Grover/Grover_core.cp311-win_amd64.pyd
pyqpanda_alg/Grover/__init__.py
pyqpanda_alg/HHL/HHL.cp311-win_amd64.pyd
pyqpanda_alg/HHL/_HHL.cp311-win_amd64.pyd
pyqpanda_alg/HHL/_HHL.pyi
pyqpanda_alg/HHL/__init__.py
pyqpanda_alg/QAE/QAE.cp311-win_amd64.pyd
pyqpanda_alg/QAE/__init__.py
pyqpanda_alg/QAOA/__init__.py
pyqpanda_alg/QAOA/default_circuits.cp311-win_amd64.pyd
pyqpanda_alg/QAOA/dstate.cp311-win_amd64.pyd
pyqpanda_alg/QAOA/qaoa.cp311-win_amd64.pyd
pyqpanda_alg/QAOA/spsa.cp311-win_amd64.pyd
pyqpanda_alg/QARM/__init__.py
pyqpanda_alg/QARM/qarm.cp311-win_amd64.pyd
pyqpanda_alg/QARM/dataset/data1.txt
pyqpanda_alg/QARM/dataset/data2.txt
pyqpanda_alg/QARM/dataset/data3.txt
pyqpanda_alg/QCmp/QCmp.cp311-win_amd64.pyd
pyqpanda_alg/QCmp/__init__.py
pyqpanda_alg/QKmeans/QuantumKmeans.cp311-win_amd64.pyd
pyqpanda_alg/QKmeans/__init__.py
pyqpanda_alg/QKmeans/dataset/Iris.csv
pyqpanda_alg/QPCA/QPCA.cp311-win_amd64.pyd
pyqpanda_alg/QPCA/__init__.py
pyqpanda_alg/QSEncode/QSEncode.cp311-win_amd64.pyd
pyqpanda_alg/QSEncode/__init__.py
pyqpanda_alg/QSVD/QSVD.cp311-win_amd64.pyd
pyqpanda_alg/QSVD/__init__.py
pyqpanda_alg/QSVM/__init__.py
pyqpanda_alg/QSVM/quantum_kernel_svm.cp311-win_amd64.pyd
pyqpanda_alg/QSVM/dataset/qsvm_samples.txt
pyqpanda_alg/QSVM/dataset/qsvm_test_features.txt
pyqpanda_alg/QSVM/dataset/qsvm_test_labels.txt
pyqpanda_alg/QSVM/dataset/qsvm_train_features.txt
pyqpanda_alg/QSVM/dataset/qsvm_train_labels.txt
pyqpanda_alg/QSVR/QSVR.cp311-win_amd64.pyd
pyqpanda_alg/QSVR/__init__.py
pyqpanda_alg/QUBO/QUBO.cp311-win_amd64.pyd
pyqpanda_alg/QUBO/__init__.py
pyqpanda_alg/QmRMR/QmRMR_core.cp311-win_amd64.pyd
pyqpanda_alg/QmRMR/__init__.py
pyqpanda_alg/VQE/__init__.py
pyqpanda_alg/VQE/_vqe.cp311-win_amd64.pyd
pyqpanda_alg/VQE/_vqe.pyi
pyqpanda_alg/VQE/vqe.cp311-win_amd64.pyd
pyqpanda_alg/extensions/_EXTENSIONS.cp311-win_amd64.pyd
pyqpanda_alg-2.0.0.dist-info/LICENSE
pyqpanda_alg-2.0.0.dist-info/METADATA
pyqpanda_alg-2.0.0.dist-info/WHEEL
pyqpanda_alg-2.0.0.dist-info/top_level.txt
pyqpanda_alg-2.0.0.dist-info/RECORD
