Metadata-Version: 2.2
Name: pyqpanda_alg
Version: 2.0.0
Summary: A Quantum Algorithm Development and Runtime Environment Kit, based on pyqpanda.
Author: OriginQ
License: Apache Licence
Classifier: Development Status :: 4 - Beta
Classifier: Operating System :: MacOS :: MacOS X
Classifier: Operating System :: Microsoft :: Windows :: Windows 10
Classifier: Operating System :: POSIX :: Linux
Classifier: Topic :: Software Development :: Libraries :: Python Modules
Classifier: Programming Language :: Python
Classifier: Programming Language :: Python :: 3.10
Classifier: Programming Language :: Python :: 3.11
Classifier: Programming Language :: Python :: 3.12
License-File: LICENSE
Requires-Dist: numpy>=1.17
Requires-Dist: matplotlib>=3.3
Requires-Dist: pydot
Requires-Dist: scipy
Requires-Dist: sympy
Requires-Dist: mypy>=1.14
Requires-Dist: requests
Requires-Dist: pycryptodome
Requires-Dist: sphinx-autoapi
Requires-Dist: pyqpanda3
Dynamic: author
Dynamic: classifier
Dynamic: license
Dynamic: requires-dist
Dynamic: summary
